setup.py
zoolander/__init__.py
zoolander/colors.py
zoolander/shorthand.py
zoolander/stylesheets.py
zoolander/units.py
zoolander.egg-info/PKG-INFO
zoolander.egg-info/SOURCES.txt
zoolander.egg-info/dependency_links.txt
zoolander.egg-info/top_level.txt