Metadata-Version: 1.0
Name: zoolander
Version: 0.1
Summary: A pure Python DSL for CSS
Home-page: http://github.com/fitzgen/zoolander
Author: Nick Fitzgerald
Author-email: fitzgen@gmail.com
License: MIT
Platform: UNKNOWN
